tacosdedatos_utils/__init__.py
tacosdedatos_utils/__main__.py
tacosdedatos_utils/example.py
tacosdedatos_utils/manejo_de_archivos.py
tacosdedatos_utils/manejo_de_datos.py
tacosdedatos_utils/manejo_de_proyectos.py
tacosdedatos_utils/py.typed
tacosdedatos_utils/viz.py
tacosdedatos_utils-1.3.0.dist-info/entry_points.txt
tacosdedatos_utils-1.3.0.dist-info/LICENSE
tacosdedatos_utils-1.3.0.dist-info/WHEEL
tacosdedatos_utils-1.3.0.dist-info/METADATA
tacosdedatos_utils-1.3.0.dist-info/RECORD
