Metadata-Version: 2.1
Name: tacosdedatos-utils
Version: 1.3.0
Summary: Una coleccion de herramientas para facilitar el analisis y visualizacion de datos por @tacosdedatos.
Home-page: https://github.com/tacosdedatos/tacosdedatos-utils
License: GPL-3.0-only
Keywords: utils,tacosdedatos
Author: tacosdedatos
Author-email: chekos@tacosdedatos.com
Requires-Python: >=3.7,<4.0
Classifier: Development Status :: 3 - Alpha
Classifier: Intended Audience :: Developers
Classifier: License :: OSI Approved :: GNU General Public License v3 (GPLv3)
Classifier: Operating System :: OS Independent
Classifier: Programming Language :: Python :: 3
Classifier: Programming Language :: Python :: 3.7
Classifier: Programming Language :: Python :: 3.8
Classifier: Topic :: Software Development :: Libraries :: Python Modules
Requires-Dist: defusedxml (>=0.6.0,<0.7.0)
Requires-Dist: importlib_metadata (>=1.6.0,<2.0.0); python_version < "3.8"
Requires-Dist: ipython (>=7.16.1,<8.0.0)
Requires-Dist: pandas (>=1.0.0,<2.0.0)
Requires-Dist: rich (>=2.2.2,<3.0.0)
Requires-Dist: typer[all] (>=0.2.1,<0.3.0)
Project-URL: Repository, https://github.com/tacosdedatos/tacosdedatos-utils
